drawranflow/__init__.py
drawranflow/admin.py
drawranflow/apps.py
drawranflow/forms.py
drawranflow/models.py
drawranflow/tests.py
drawranflow/urls.py
drawranflow/views.py
drawranflow/migrations/__init__.py
drawranflow/servicelogic/__init__.py
drawranflow/servicelogic/handlers/__init__.py
drawranflow/servicelogic/handlers/anamaloy.py
drawranflow/servicelogic/handlers/files_handler_lte.py
drawranflow/servicelogic/handlers/files_handler_sa.py
drawranflow/servicelogic/handlers/message_handler_lte.py
drawranflow/servicelogic/handlers/message_handler_lte_combined_mesg.py
drawranflow/servicelogic/handlers/message_handler_sa.py
drawranflow/servicelogic/handlers/message_handler_sa_combined_mesg.py
drawranflow/servicelogic/handlers/nsa_utils.py
drawranflow/servicelogic/handlers/processPacketslte.py
drawranflow/servicelogic/handlers/processPacketssa.py
drawranflow/servicelogic/handlers/statsHandler_lte.py
drawranflow/servicelogic/handlers/statsHandler_sa.py
drawranflow/servicelogic/handlers/utils_sa.py
drawranflow/servicelogic/intfconfig/cos_codes.json
drawranflow/servicelogic/intfconfig/e1ap_proc.json
drawranflow/servicelogic/intfconfig/est_cause.json
drawranflow/servicelogic/intfconfig/f1ap_cause.json
drawranflow/servicelogic/intfconfig/f1ap_proc.json
drawranflow/servicelogic/intfconfig/lte_proc.json
drawranflow/servicelogic/intfconfig/lte_rrc_proc.json
drawranflow/servicelogic/intfconfig/msg_directions.json
drawranflow/servicelogic/intfconfig/nas_cause.json
drawranflow/servicelogic/intfconfig/nas_proc.json
drawranflow/servicelogic/intfconfig/ngap_cause.json
drawranflow/servicelogic/intfconfig/ngap_proc.json
drawranflow/servicelogic/intfconfig/rrc_cause.json
drawranflow/servicelogic/intfconfig/rrc_proc.json
drawranflow/servicelogic/intfconfig/s1ap_proc.json
drawranflow/servicelogic/intfconfig/x2ap_proc.json
drawranflow/servicelogic/intfconfig/xnap_cause.json
drawranflow/servicelogic/intfconfig/xnap_proc.json
drawranflow/static/my_java_script.js
ranshark-1.0.0.38.dist-info/METADATA
ranshark-1.0.0.38.dist-info/WHEEL
ranshark-1.0.0.38.dist-info/top_level.txt
ranshark-1.0.0.38.dist-info/RECORD
