Metadata-Version: 2.1
Name: ranshark
Version: 1.0.0.38
Summary: A friendly 4G-LTE/5G o-ran packet analyzing tool with GUI interface.
Home-page: UNKNOWN
Author: ugandhar
Author-email: ugandhar.nellore@gmail.com
License: Apache-2.0
Keywords: ran,5g,lte,5g analyzer,ranshark,4g
Platform: UNKNOWN
Classifier: Intended Audience :: Telecommunications Industry
Classifier: Intended Audience :: Education
Classifier: Intended Audience :: End Users/Desktop
Classifier: Programming Language :: Python :: 3.10
Requires-Dist: Django
Requires-Dist: pandas ==2.1.4
Requires-Dist: pyshark ==0.6
Requires-Dist: psycopg2
Requires-Dist: psycopg2-binary
Requires-Dist: numpy ==1.26.2
Requires-Dist: importlib
Requires-Dist: openpyxl
